cade/__init__.py
cade/cade_.py
temporal_embeddings_compass-0.4.5.dist-info/METADATA
temporal_embeddings_compass-0.4.5.dist-info/WHEEL
temporal_embeddings_compass-0.4.5.dist-info/licenses/LICENSE
temporal_embeddings_compass-0.4.5.dist-info/RECORD
