Metadata-Version: 2.3
Name: temporal_embeddings_compass
Version: 0.4.5
Summary: A package for creating temporal embeddings with a compass
Project-URL: Homepage, https://github.com/danilka4/ttec.git
Project-URL: Bug Tracker, https://github.com/danilka4/tec/pulls
Author-email: Daniel Palamarchuk <d4n1elp@vt.edu>
License-File: LICENSE
Classifier: License :: OSI Approved :: MIT License
Classifier: Operating System :: OS Independent
Classifier: Programming Language :: Python :: 3
Requires-Python: >=3.7
Requires-Dist: hdbscan
Requires-Dist: numpy
Requires-Dist: pandas
Requires-Dist: plotly
Requires-Dist: scipy
Requires-Dist: umap-learn
